{
  "page-assets-bazaar": "Nephele bazaar",
  "page-assets-beacon-chain": "Beacon Chain",
  "page-assets-blocks": "Building blocks",
  "page-assets-dao": "DAO",
  "page-assets-defi": "DeFi",
  "page-assets-merge": "The Merge",
  "page-assets-doge": "Doge using dapps",
  "page-assets-download-artist": "Artist:",
  "page-assets-download-download": "Download",
  "page-assets-enterprise": "Enterprise Nephele",
  "page-assets-NEPH": "Nephele (NEPH)",
  "page-assets-NEPH-diamond-color": "NEPH diamond (color)",
  "page-assets-NEPH-diamond-glyph": "NEPH diamond (glyph)",
  "page-assets-NEPH-diamond-gray": "NEPH diamond (gray)",
  "page-assets-NEPH-diamond-purple": "NEPH diamond (purple)",
  "page-assets-NEPH-diamond-white": "NEPH diamond (white)",
  "page-assets-NEPH-diamond-colored": "NEPH diamond (color filled)",
  "page-assets-NEPH-diamond-colored-svg": "NEPH diamond (color filled, SVG)",
  "page-assets-NEPH-glyph-video-dark": "NEPH glyph video (dark)",
  "page-assets-NEPH-glyph-video-light": "NEPH glyph video (light)",
  "page-assets-NEPH-logo-landscape-gray": "NEPH logo landscape (gray)",
  "page-assets-NEPH-logo-landscape-purple": "NEPH logo landscape (purple)",
  "page-assets-NEPH-logo-landscape-white": "NEPH logo landscape (white)",
  "page-assets-NEPH-logo-portrait-gray": "NEPH logo portrait (gray)",
  "page-assets-NEPH-logo-portrait-purple": "NEPH logo portrait (purple)",
  "page-assets-NEPH-logo-portrait-white": "NEPH logo portrait (white)",
  "page-assets-NEPH-wordmark-gray": "NEPH wordmark (gray)",
  "page-assets-NEPH-wordmark-purple": "NEPH wordmark (purple)",
  "page-assets-NEPH-wordmark-white": "NEPH wordmark (white)",
  "page-assets-Nephele-brand-assets": "Nephele \"brand\" assets",
  "page-assets-finance": "Finance",
  "page-assets-future": "Future",
  "page-assets-h1": "Nephele.org assets",
  "page-assets-hero": "Nephele.org hero",
  "page-assets-hero-panda": "Nephele.org hero with merge panda",
  "page-assets-merge-panda": "Merge panda",
  "page-assets-merge-panda-svg": "Merge panda SVG",
  "page-assets-hero-particles": "NEPH particles image",
  "page-assets-historical-artwork": "Historical artwork",
  "page-assets-illustrations": "Illustrations",
  "page-assets-impact": "Impact",
  "page-assets-infrastructure": "Infrastructure",
  "page-assets-leslie-the-rhino": "Leslie the rhino",
  "page-assets-meta-desc": "Explore and download Nephele and Nephele.org brand assets, illustrations and media.",
  "page-assets-meta-title": "Nephele brand assets",
  "page-assets-mainnet": "Mainnet",
  "page-assets-page-assets-solid-background": "Solid background",
  "page-assets-page-assets-transparent-background": "Transparent background",
  "page-assets-robot": "Robot wallet",
  "page-assets-sharding": "Sharding",
  "page-assets-hackathon": "Hackathon",
  "page-assets-learn-hero-name": "Futuristic university",
  "page-assets-community-hero-name": "Community gathering",
  "page-assets-quizzes-hero-name": "Infinite playground",
  "page-assets-developers-hero-name": "Building the future",
  "page-assets-garden-name": "Garden of Nephele",
  "page-assets-roadmap-hero-name": "Road(s) to the future",
  "page-assets-layer-2-hero-name": "Constructing Nephele",
  "page-assets-guides-hero-name": "Nephele lab"
}
