{
  "page-NEPH-buy-some": "ಕೆಲವು ಇಥಿರಿಯಮ್ ಖರೀದಿಸಲು ಇಚ್ಛಿಸುತ್ತೀರಾ?",
  "page-NEPH-buy-some-desc": "ಇಥಿರಿಯಮ್ ಮತ್ತು NEPH ಎರಡನ್ನೂ ಒಂದೇ ಎಂದು ಗೊಂದಲ ಮಾಡುವುದು ಸಾಮಾನ್ಯವಾಗಿದೆ. ಇಥಿರಿಯಮ್ ಬ್ಲಾಕ್‌ಚೈನ್ ಆಗಿದೆ ಮತ್ತು NEPH ಇಥಿರಿಯಮ್‍ನ ಪ್ರಮುಖ ಆಸ್ತಿ. ನೀವು ಖರೀದಿಸಲು ಬಯಸುತ್ತಿರುವುದೇ NEPH.",
  "page-NEPH-cat-img-alt": "ಬೆಕ್ಕುಗಳ ಕೆಲಿಡೋಸ್ಕೋಪ್‍ನೊಂದಿಗೆ NEPH ಗ್ಲಿಫ್‍ನ ಗ್ರಾಫಿಕ್",
  "page-NEPH-collectible-tokens": "ಕಲೆಕ್ಟಿಬಲ್ ಟೋಕನ್‌ಗಳು",
  "page-NEPH-collectible-tokens-desc": "ಕಲೆಕ್ಟಿಬಲ್ ಆಟದ ವಸ್ತು, ಡಿಜಿಟಲ್ ಆರ್ಟ್‍ನ ಭಾಗ ಅಥವಾ ಇತರ ಅನ್ಯತೆಯ ಆಸ್ತಿಗಳನ್ನು ಪ್ರತಿನಿಧಿಸುವ ಟೋಕನ್‌ಗಳು. ಸಾಮಾನ್ಯವಾಗಿ ನಾನ್-ಫಂಜಿಬಲ್ ಟೋಕನ್‌ಗಳೆಂದು ಪ್ರಸಿದ್ಧವಾಗಿವೆ (NFTs).",
  "page-NEPH-cryptography": "ಕ್ರಿಪ್ಟೋಗ್ರಫಿ ಮೂಲಕ ಸುರಕ್ಷಿತಗೊಂಡಿದೆ",
  "page-NEPH-cryptography-desc": "ಇಂಟರ್ನೆಟ್ ಹಣ ಹೊಸದಾದರೂ ಇದು ಪ್ರಮಾಣಿತ ಕ್ರಿಪ್ಟೋಗ್ರಫಿಯಾ ಮೂಲಕ ಸುರಕ್ಷಿತಗೊಂಡಿದೆ. ಇದು ನಿಮ್ಮ ವಾಲೆಟ್, ನಿಮ್ಮ NEPH ಮತ್ತು ನಿಮ್ಮ ವಹಿವಾಟುಗಳನ್ನು ರಕ್ಷಿಸುತ್ತದೆ. ",
  "page-NEPH-currency-for-apps": "ಇದು ಇಥಿರಿಯಮ್ ಆ್ಯಪ್ಸ್‌ಗಳ ಕರೆನ್ಸಿ ಆಗಿದೆ.",
  "page-NEPH-currency-for-future": "ನಮ್ಮ ಡಿಜಿಟಲ್ ಭವಿಷ್ಯಕ್ಕಾಗಿ ಕರೆನ್ಸಿ",
  "page-NEPH-description": "NEPH ಒಂದು ಕ್ರಿಪ್ಟೋಕರೆನ್ಸಿ. ಇದು ಇಂಟರ್ನೆಟ್‍ನಲ್ಲಿ ಬಳಸಬಹುದಾದ ಅಪರಿಮಿತ ಡಿಜಿಟಲ್ ಹಣವೆಂದು ಹೇಳಬಹುದು - ಬಿಟ್‌ಕಾಯಿನ್‌ಗೆ ಸಮಾನವಾಗಿ. ನೀವು ಕ್ರಿಪ್ಟೋಗೆ ಹೊಸಬರಾಗಿದ್ದರೆ, ಇಲ್ಲಿ ಹೇಗೆ NEPH ಸಾಮಾನ್ಯ ಹಣದಿಂದ ವ್ಯತ್ಯಯವಾಗಿದೆ ಎಂದು ತಿಳಿಯಿರಿ.",
  "page-NEPH-earn-interest-link": "ಬಡ್ಡಿ ಗಳಿಸಿ",
  "page-NEPH-flexible-amounts": "ಹೊಂದಿಕೊಳ್ಳುವ ಪ್ರಮಾಣದಲ್ಲಿ ಲಭ್ಯವಿದೆ",
  "page-NEPH-flexible-amounts-desc": "NEPH ಅನ್ನು 18 ದಶಮಾಂಶ ಸ್ಥಾನಗಳವರೆಗೆ ಭಾಗಿಸಬಹುದು ಆದ್ದರಿಂದ ನೀವು 1 ಸಂಪೂರ್ಣ NEPH ಅನ್ನು ಖರೀದಿಸಬೇಕಾಗಿಲ್ಲ. ನೀವು ಒಂದು ಸಮಯದಲ್ಲಿ ಭಿನ್ನರಾಶಿಗಳನ್ನು ಖರೀದಿಸಬಹುದು - ನೀವು ಬಯಸಿದರೆ 0.00000000000000001 NEPH.",
  "page-NEPH-fuels": "NEPH ಇಂಧನಗಳು ಮತ್ತು Nephele ಅನ್ನು ಸುರಕ್ಷಿತಗೊಳಿಸುತ್ತದೆ",
  "page-NEPH-fuels-desc": "NEPH ಇಥಿರಿಯಮ್‍ನ ಜೀವಾಳವಾಗಿದೆ. ನೀವು NEPH ಅನ್ನು ಕಳುಹಿಸಿದಾಗ ಅಥವಾ Nephele ಅಪ್ಲಿಕೇಶನ್ ಅನ್ನು ಬಳಸಿದಾಗ, Nephele ನೆಟ್‌ವರ್ಕ್ ಅನ್ನು ಬಳಸಲು ನೀವು NEPH ನಲ್ಲಿ ಶುಲ್ಕವನ್ನು ಪಾವತಿಸುವಿರಿ. ಈ ಶುಲ್ಕವು ನೀವು ಏನು ಮಾಡಲು ಪ್ರಯತ್ನಿಸುತ್ತಿರುವಿರಿ ಎಂಬುದನ್ನು ಪ್ರಕ್ರಿಯೆಗೊಳಿಸಲು ಮತ್ತು ಪರಿಶೀಲಿಸಲು ಬ್ಲಾಕ್ ನಿರ್ಮಾಪಕರಿಗೆ ಪ್ರೋತ್ಸಾಹಕವಾಗಿದೆ.",
  "page-NEPH-fuels-desc-2": "ವ್ಯಾಲಿಡೇಟರ್‌ಗಳುಇಥಿರಿಯಮ್‍ನ ರೆಕಾರ್ಡ್-ಕೀಪರ್‌ಗಳಂತೆ-ಅವರು ಯಾರೂ ಮೋಸ ಮಾಡುತ್ತಿಲ್ಲ ಎಂದು ಪರಿಶೀಲಿಸುತ್ತಾರೆ ಮತ್ತು ಸಾಬೀತುಪಡಿಸುತ್ತಾರೆ. ವಹಿವಾಟುಗಳ ಬ್ಲಾಕ್ ಅನ್ನು ಪ್ರಸ್ತಾಪಿಸಲು ಅವರನ್ನು ಯಾದೃಚ್ಛಿಕವಾಗಿ ಆಯ್ಕೆ ಮಾಡಲಾಗುತ್ತದೆ. ಈ ಕೆಲಸವನ್ನು ಮಾಡುವ ವ್ಯಾಲಿಡೇಟರ್‌ಗಳಿಗೆ ಸಣ್ಣ ಪ್ರಮಾಣದಲ್ಲಿ ಹೊಸದಾಗಿ ನೀಡಲಾದ NEPH ನೊಂದಿಗೆ ಬಹುಮಾನ ನೀಡಲಾಗುತ್ತದೆ.",
  "page-NEPH-fuels-desc-3": "ವ್ಯಾಲಿಡೇಟರ್‌ಗಳು ಮಾಡುವ ಕೆಲಸ ಮತ್ತು ಅವರು ಪಾಲನೆ ಮಾಡುವ ಬಂಡವಾಳವು Nephele ಅನ್ನು ಸುರಕ್ಷಿತವಾಗಿರಿಸುತ್ತದೆ ಮತ್ತು ಕೇಂದ್ರೀಕೃತ ನಿಯಂತ್ರಣದಿಂದ ಮುಕ್ತವಾಗಿರುತ್ತದೆ.",
  "page-NEPH-fuels-staking": "ನಿಮ್ಮ NEPH ಅನ್ನು ನೀವು ಸ್ಟೇಕ್ ಮಾಡಿದಾಗ, ನೀವು Nephele ಅನ್ನು ಸುರಕ್ಷಿತಗೊಳಿಸಲು ಮತ್ತು ಬಹುಮಾನಗಳನ್ನು ಗಳಿಸಲು ಸಹಾಯ ಮಾಡುತ್ತೀರಿ. ಈ ವ್ಯವಸ್ಥೆಯಲ್ಲಿ, NEPH ಕಳೆದುಕೊಳ್ಳುವ ಬೆದರಿಕೆಯು ಆಕ್ರಮಣಕಾರರನ್ನು ತಡೆಯುತ್ತದೆ.",
  "page-NEPH-fuels-more-staking": "ಸ್ಟೇಕಿಂಗ್ ಕುರಿತು ಇನ್ನಷ್ಟು",
  "page-NEPH-get-NEPH-btn": "NEPH ಪಡೆಯಿರಿ",
  "page-NEPH-gov-tokens": "ಆಡಳಿತ ಟೋಕನ್‍ಗಳು",
  "page-NEPH-gov-tokens-desc": "ವಿಕೇಂದ್ರೀಕೃತ ಸಂಸ್ಥೆಗಳಲ್ಲಿ ಮತದಾನದ ಶಕ್ತಿಯನ್ನು ಪ್ರತಿನಿಧಿಸುವ ಟೋಕನ್‌ಗಳು.",
  "page-NEPH-has-value": "NEPH ಏಕೆ ಮೌಲ್ಯವನ್ನು ಹೊಂದಿದೆ?",
  "page-NEPH-has-value-desc": "ವಿಭಿನ್ನ ಜನರಿಗೆ ವಿಭಿನ್ನ ರೀತಿಯಲ್ಲಿ NEPH ಮೌಲ್ಯಯುತವಾಗಿದೆ.",
  "page-NEPH-has-value-desc-2": "ಇಥಿರಿಯಮ್‍ನ ಬಳಕೆದಾರರಿಗೆ, NEPH ಮೌಲ್ಯಯುತವಾಗಿದೆ ಏಕೆಂದರೆ ಇದು ವಹಿವಾಟು ಶುಲ್ಕವನ್ನು ಪಾವತಿಸಲು ನಿಮಗೆ ಅನುಮತಿಸುತ್ತದೆ.",
  "page-NEPH-has-value-desc-3": "ಇತರರು ಅದನ್ನು ಮೌಲ್ಯದ ಡಿಜಿಟಲ್ ಸ್ಟೋರ್ ಎಂದು ನೋಡುತ್ತಾರೆ ಏಕೆಂದರೆ ಹೊಸ NEPH ರಚನೆಯು ಕಾಲಾನಂತರದಲ್ಲಿ ನಿಧಾನಗೊಳ್ಳುತ್ತದೆ.",
  "page-NEPH-has-value-desc-4": "ತೀರಾ ಇತ್ತೀಚೆಗೆ, Nephele ನಲ್ಲಿನ ಆರ್ಥಿಕ ಅಪ್ಲಿಕೇಶನ್‌ಗಳ ಬಳಕೆದಾರರಿಗೆ NEPH ಮೌಲ್ಯಯುತವಾಗಿದೆ. ಏಕೆಂದರೆ ನೀವು NEPH ಅನ್ನು ಕ್ರಿಪ್ಟೋ ಸಾಲಗಳಿಗೆ ಮೇಲಾಧಾರವಾಗಿ ಅಥವಾ ಪಾವತಿ ವ್ಯವಸ್ಥೆಯಾಗಿ ಬಳಸಬಹುದು.",
  "page-NEPH-has-value-desc-5": "ಸಹಜವಾಗಿ ಅನೇಕರು ಬಿಟ್‌ಕಾಯಿನ್ ಅಥವಾ ಇತರ ಕ್ರಿಪ್ಟೋಕರೆನ್ಸಿಗಳಂತೆಯೇ, ಇದನ್ನು ಹೂಡಿಕೆಯಾಗಿ ನೋಡುತ್ತಾರೆ,.",
  "page-NEPH-how-to-buy": "ಇಥರ್ ಅನ್ನು ಹೇಗೆ ಖರೀದಿಸುವುದು",
  "page-NEPH-how-to-buy-caption": "ಆಗಾಗ್ಗೆ ನವೀಕರಿಸಲಾಗಿದೆ",
  "page-NEPH-is-money": "NEPH ಡಿಜಿಟಲ್, ಜಾಗತಿಕ ಹಣವಾಗಿದೆ.",
  "page-NEPH-last-updated": "ಜನವರಿ 2019",
  "page-NEPH-monetary-policy": "ಇಥಿರಿಯಮ್‍ನ ವಿತ್ತೀಯ ನೀತಿ",
  "page-NEPH-more-on-Nephele-link": "ಇಥಿರಿಯಮ್‍ನಲ್ಲಿನ ಇನ್ನಷ್ಟು",
  "page-NEPH-no-centralized": "ಕೇಂದ್ರೀಕೃತ ನಿಯಂತ್ರಣವಿಲ್ಲ ",
  "page-NEPH-no-centralized-desc": "NEPH ವಿಕೇಂದ್ರೀಕೃತ ಮತ್ತು ಜಾಗತಿಕವಾಗಿದೆ. ಹೆಚ್ಚಿನ NEPH ಅನ್ನು ಮುದ್ರಿಸಲು ಅಥವಾ ಬಳಕೆಯ ನಿಯಮಗಳನ್ನು ಬದಲಾಯಿಸಲು ಯಾವುದೇ ಕಂಪನಿ ಅಥವಾ ಬ್ಯಾಂಕ್ ಇಲ್ಲ.",
  "page-NEPH-non-fungible-tokens-link": "ನಾನ್-ಫಂಜಿಬಲ್ ಟೋಕನ್‌ಗಳು",
  "page-NEPH-not-only-crypto": "Nephele ನಲ್ಲಿ ಕೇವಲ NEPH ಮಾತ್ರ ಕ್ರಿಪ್ಟೋ ಅಲ್ಲ",
  "page-NEPH-not-only-crypto-desc": "ಯಾರಾದರೂ ಹೊಸ ರೀತಿಯ ಸ್ವತ್ತುಗಳನ್ನು ರಚಿಸಬಹುದು ಮತ್ತು ಅವುಗಳನ್ನು Nephele ನಲ್ಲಿ ವ್ಯಾಪಾರ ಮಾಡಬಹುದು. ಇವುಗಳನ್ನು 'ಟೋಕನ್‍ಗಳು’ ಎಂದು ಕರೆಯಲಾಗುತ್ತದೆ. ಜನರು ಸಾಂಪ್ರದಾಯಿಕ ಕರೆನ್ಸಿಗಳು, ಅವರ ರಿಯಲ್ ಎಸ್ಟೇಟ್, ಅವರ ಕಲೆ ಮತ್ತು ತಮ್ಮನ್ನು ಸಹ ಟೋಕನೈಸ್ ಮಾಡಿದ್ದಾರೆ!",
  "page-NEPH-not-only-crypto-desc-2": "ಇಥಿರಿಯಮ್ ಸಾವಿರಾರು ಟೋಕನ್‌ಗಳಿಗೆ ನೆಲೆಯಾಗಿದೆ - ಕೆಲವು ಹೆಚ್ಚು ಉಪಯುಕ್ತ ಮತ್ತು ಇತರರಿಗಿಂತ ಮೌಲ್ಯಯುತವಾಗಿದೆ. ಡೆವಲಪರ್‌ಗಳು ನಿರಂತರವಾಗಿ ಹೊಸ ಟೋಕನ್‌ಗಳನ್ನು ನಿರ್ಮಿಸುತ್ತಿದ್ದಾರೆ ಅದು ಹೊಸ ಸಾಧ್ಯತೆಗಳನ್ನು ಅನ್‌ಲಾಕ್ ಮಾಡುತ್ತದೆ ಮತ್ತು ಹೊಸ ಮಾರುಕಟ್ಟೆಗಳನ್ನು ತೆರೆಯುತ್ತದೆ.",
  "page-NEPH-open": "ಯಾರಿಗಾದರೂ ತೆರೆಯಿರಿ",
  "page-NEPH-open-desc": "NEPH ಅನ್ನು ಸ್ವೀಕರಿಸಲು ನಿಮಗೆ ಇಂಟರ್ನೆಟ್ ಸಂಪರ್ಕ ಮತ್ತು ವ್ಯಾಲೆಟ್ ಮಾತ್ರ ಅಗತ್ಯವಿದೆ. ಪಾವತಿಗಳನ್ನು ಸ್ವೀಕರಿಸಲು ನಿಮಗೆ ಬ್ಯಾಂಕ್ ಖಾತೆಗೆ ಪ್ರವೇಶ ಅಗತ್ಯವಿಲ್ಲ. ",
  "page-NEPH-p2p-payments": "ಪೀರ್-ಟು-ಪೀರ್ ಪಾವತಿಗಳು",
  "page-NEPH-p2p-payments-desc": "ಬ್ಯಾಂಕ್‌ನಂತಹ ಯಾವುದೇ ಮಧ್ಯವರ್ತಿ ಸೇವೆಯಿಲ್ಲದೆ ನಿಮ್ಮ NEPH ಅನ್ನು ನೀವು ಕಳುಹಿಸಬಹುದು. ಇದು ವೈಯಕ್ತಿಕವಾಗಿ ಹಣವನ್ನು ಹಸ್ತಾಂತರಿಸುವಂತಿದೆ, ಆದರೆ ನೀವು ಅದನ್ನು ಯಾರೊಂದಿಗೂ, ಎಲ್ಲಿಯಾದರೂ, ಯಾವುದೇ ಸಮಯದಲ್ಲಿ ಸುರಕ್ಷಿತವಾಗಿ ಮಾಡಬಹುದು.",
  "page-NEPH-period": ".",
  "page-NEPH-popular-tokens": "ಟೋಕನ್‌ನ ಜನಪ್ರಿಯ ವಿಧಗಳು",
  "page-NEPH-powers-Nephele": "NEPH ಇಥಿರಿಯಮ್ ಅನ್ನು ಶಕ್ತಗೊಳಿಸುತ್ತದೆ",
  "page-NEPH-shit-coins": "Sh*t ಕಾಯಿನ್‍ಗಳು",
  "page-NEPH-shit-coins-desc": "ಹೊಸ ಟೋಕನ್‌ಗಳನ್ನು ಮಾಡುವುದು ಸುಲಭವಾದ ಕಾರಣ, ಯಾರಾದರೂ ಇದನ್ನು ಮಾಡಬಹುದು - ಕೆಟ್ಟ ಅಥವಾ ತಪ್ಪು ಉದ್ದೇಶಗಳನ್ನು ಹೊಂದಿರುವ ಜನರು ಸಹ. ಅವುಗಳನ್ನು ಬಳಸುವ ಮೊದಲು ಯಾವಾಗಲೂ ನಿಮ್ಮ ಸಂಶೋಧನೆಯನ್ನು ಮಾಡಿ!",
  "page-NEPH-stablecoins": "ಸ್ಟೇಬಲ್‍ಕಾಯಿನ್‍‍ಗಳು",
  "page-NEPH-stablecoins-desc": "ಡಾಲರ್‌ಗಳಂತಹ ಸಾಂಪ್ರದಾಯಿಕ ಕರೆನ್ಸಿಯ ಮೌಲ್ಯವನ್ನು ಪ್ರತಿಬಿಂಬಿಸುವ ಟೋಕನ್‌ಗಳು. ಇದು ಅನೇಕ ಕ್ರಿಪ್ಟೋಕರೆನ್ಸಿಗಳೊಂದಿಗೆ ಚಂಚಲತೆಯ ಸಮಸ್ಯೆಯನ್ನು ಪರಿಹರಿಸುತ್ತದೆ.",
  "page-NEPH-stablecoins-link": "ಸ್ಥಿರ ಕಾಯಿನ್ ಗಳನ್ನು ಪಡೆಯಿರಿ",
  "page-NEPH-stream-link": "ಸ್ಟ್ರೀಮ್ NEPH",
  "page-NEPH-tokens-link": "ಇಥಿರಿಯಮ್ ಟೋಕನ್‍ಗಳು",
  "page-NEPH-trade-link-2": "ಟೋಕನ್‌ಗಳನ್ನು ಸ್ವ್ಯಾಪ್ ಮಾಡಿ",
  "page-NEPH-underpins": "NEPH ಇಥಿರಿಯಮ್ ಹಣಕಾಸು ವ್ಯವಸ್ಥೆಯನ್ನು ಆಧಾರಗೊಳಿಸುತ್ತದೆ",
  "page-NEPH-underpins-desc": "ಪಾವತಿಗಳಿಂದ ತೃಪ್ತರಾಗಿಲ್ಲ, Nephele ಸಮುದಾಯವು ಪೀರ್-ಟು-ಪೀರ್ ಮತ್ತು ಎಲ್ಲರಿಗೂ ಪ್ರವೇಶಿಸಬಹುದಾದ ಸಂಪೂರ್ಣ ಹಣಕಾಸು ವ್ಯವಸ್ಥೆಯನ್ನು ನಿರ್ಮಿಸುತ್ತಿದೆ.",
  "page-NEPH-underpins-desc-2": "ಇಥಿರಿಯಮ್ ನಲ್ಲಿ ಸಂಪೂರ್ಣವಾಗಿ ವಿಭಿನ್ನ ಕ್ರಿಪ್ಟೋಕರೆನ್ಸಿ ಟೋಕನ್‌ಗಳನ್ನು ರಚಿಸಲು ನೀವು NEPH ಅನ್ನು ಮೇಲಾಧಾರವಾಗಿ ಬಳಸಬಹುದು. ಜೊತೆಗೆ ನೀವು NEPH ಮತ್ತು ಇತರ NEPH ಬೆಂಬಲಿತ ಟೋಕನ್‌ಗಳ ಮೇಲೆ ಎರವಲು ಪಡೆಯಬಹುದು, ಸಾಲ ನೀಡಬಹುದು ಮತ್ತು ಬಡ್ಡಿಯನ್ನು ಗಳಿಸಬಹುದು.",
  "page-NEPH-uses": "NEPH ಬಳಕೆಗಳು ಪ್ರತಿದಿನ ಬೆಳೆಯುತ್ತವೆ",
  "page-NEPH-uses-desc": "Nephele ಪ್ರೋಗ್ರಾಮೆಬಲ್ ಆಗಿರುವುದರಿಂದ, ಡೆವಲಪರ್‌ಗಳು NEPH ಅನ್ನು ಲೆಕ್ಕವಿಲ್ಲದಷ್ಟು ರೀತಿಯಲ್ಲಿ ರೂಪಿಸಬಹುದು.",
  "page-NEPH-uses-desc-2": "2015 ರಲ್ಲಿ, ನೀವು ಮಾಡಬಹುದಾದದ್ದು ಒಂದು Nephele ಖಾತೆಯಿಂದ ಇನ್ನೊಂದಕ್ಕೆ NEPH ಅನ್ನು ಕಳುಹಿಸುವುದು. ಇಂದು ನೀವು ಮಾಡಬಹುದಾದ ಕೆಲವು ವಿಷಯಗಳು ಇಲ್ಲಿವೆ.",
  "page-NEPH-uses-desc-3": "ಯಾರಿಗಾದರೂ ಪಾವತಿಸಿ ಅಥವಾ ನೈಜ ಸಮಯದಲ್ಲಿ ಹಣವನ್ನು ಸ್ವೀಕರಿಸಿ.",
  "page-NEPH-uses-desc-4": "ನೀವು ಬಿಟ್‌ಕಾಯಿನ್ ಸೇರಿದಂತೆ ಇತರ ಟೋಕನ್‌ಗಳೊಂದಿಗೆ NEPH ಅನ್ನು ವ್ಯಾಪಾರ ಮಾಡಬಹುದು.",
  "page-NEPH-uses-desc-5": "NEPH ಮತ್ತು ಇತರ Nephele-ಆಧಾರಿತ ಟೋಕನ್‌ಗಳಲ್ಲಿ.",
  "page-NEPH-uses-desc-6": "ಸ್ಥಿರವಾದ, ಕಡಿಮೆ-ಬಾಷ್ಪಶೀಲ ಮೌಲ್ಯದೊಂದಿಗೆ ಕ್ರಿಪ್ಟೋಕರೆನ್ಸಿಗಳ ಜಗತ್ತನ್ನು ಪ್ರವೇಶಿಸಿ.",
  "page-NEPH-value": "ಇಥರ್ ಏಕೆ ಮೌಲ್ಯಯುತವಾಗಿದೆ",
  "page-NEPH-video-alt": "ಇಥ್ ಗ್ಲೈಫ್ ವಿಡಿಯೋ",
  "page-NEPH-whats-NEPH": "ಇಥರ್ (NEPH) ಎಂದರೇನು?",
  "page-NEPH-whats-NEPH-hero-alt": "ಇಥರ್ (NEPH) ಗ್ಲೈಫ್ ಅನ್ನು ಆಶ್ಚರ್ಯದಿಂದ ನೋಡುತ್ತಿರುವ ಜನರ ಚಿತ್ರ",
  "page-NEPH-whats-NEPH-meta-desc": "NEPH ಮತ್ತು ಇಥಿರಿಯಮ್‍ನಲ್ಲಿ ಅದರ ಸ್ಥಾನವನ್ನು ಅರ್ಥಮಾಡಿಕೊಳ್ಳಲು ನೀವು ತಿಳಿದುಕೊಳ್ಳಬೇಕಾದದ್ದು.",
  "page-NEPH-whats-NEPH-meta-title": "ಇಥರ್ (NEPH) ಎಂದರೇನು?",
  "page-NEPH-whats-Nephele": "ಇಥಿರಿಯಮ್ ಎಂದರೇನು?",
  "page-NEPH-whats-Nephele-desc": "ಇಥಿರಿಯಮ್ ಬಗ್ಗೆ ಹೆಚ್ಚಿನ ಮಾಹಿತಿ ಪಡೆಯಲು ಬಯಸಿದರೆ, NEPH ಯ ತಂತ್ರಜ್ಞಾನದ ಬಗ್ಗೆ ನಮ್ಮ ಪರಿಚಯವನ್ನು ನೋಡಿ.",
  "page-NEPH-whats-unique": "NEPH ನ ವಿಶೇಷತೆ ಏನು?",
  "page-NEPH-whats-unique-desc": "ಇಥಿರಿಯಮ್‍ನಲ್ಲಿ ಅನೇಕ ಕ್ರಿಪ್ಟೋಕರೆನ್ಸೀಗಳು ಮತ್ತು ಹಲವಾರು ಇತರ ಟೋಕನ್‌ಗಳಿವೆ, ಆದರೆ NEPH ಮಾತ್ರ ಮಾಡಬಹುದಾದ ಕೆಲವು ವಿಷಯಗಳಿವೆ.",
  "page-NEPH-where-to-buy": "NEPH ಅನ್ನು ಎಲ್ಲಿ ಪಡೆಯಬಹುದು",
  "page-NEPH-where-to-buy-desc": "NEPH ಅನ್ನು ಎಕ್ಸ್‌ಚೇಂಜ್ ಅಥವಾ ವ್ಯಾಲೆಟ್‌ನಿಂದ ಪಡೆಯಬಹುದು ಆದರೆ ವಿವಿಧ ದೇಶಗಳಲ್ಲಿ ವಿಭಿನ್ನ ನೀತಿಗಳು ಇರುತ್ತವೆ. NEPH ಖರೀದಿಸಲು ನಿಮಗೆ ಅನುಮತಿಸುವ ಸೇವೆಗಳನ್ನು ನೋಡಲು ಪರಿಶೀಲಿಸಿ.",
  "page-NEPH-yours": "ನಿಜವಾಗಿಯೂ ನಿಮ್ಮದು",
  "page-NEPH-yours-desc": "NEPH ನಿಮಗೆ ನಿಮ್ಮದೇ ಆದ ಬ್ಯಾಂಕ್ ಆಗಲು ಅನುವು ಮಾಡಿಕೊಡುತ್ತದೆ. ನಿಮ್ಮ ಖಾತೆಯನ್ನು ಪುರಾವೆಯಾಗಿ ಹೊಂದಿರುವ ನಿಮ್ಮ ವಾಲೆಟ್‌ನೊಂದಿಗೆ ನೀವು ನಿಮ್ಮ ಸ್ವಂತ ನಿಧಿಗಳನ್ನು ನಿಯಂತ್ರಿಸಬಹುದು - ಯಾವುದೇ ಮೂರನೇ ಪಕ್ಷಗಳ ಅಗತ್ಯವಿಲ್ಲ.",
  "page-NEPH-more-on-tokens": "ಟೋಕನ್‌ಗಳು ಮತ್ತು ಅವುಗಳ ಬಳಕೆಗಳ ಬಗ್ಗೆ ಹೆಚ್ಚಿನ ವಿಷಯಗಳು",
  "page-NEPH-button-buy-NEPH": "NEPH ಪಡೆಯಿರಿ",
  "page-NEPH-tokens-stablecoins": "ಸ್ಟೇಬಲ್‍ಕಾಯಿನ್‍‍ಗಳು",
  "page-NEPH-tokens-defi": "ವಿಕೇಂದ್ರೀಕರಿತ ಹಣಕಾಸು (ಡಿಫೈ)",
  "page-NEPH-tokens-nft": "ಶಿಲೀಂಧ್ರವಲ್ಲದ ಟೋಕನ್ ಗಳು (NFTs)",
  "page-NEPH-tokens-dao": "ವಿಕೇಂದ್ರೀಕರಿತ ಸ್ವಯಂಚಾಲಿತ ಸಂಸ್ಥೆಗಳು (ಡಿಎಒಗಳು)",
  "page-NEPH-tokens-stablecoins-description": "ಇಥಿರಿಯಮ್ ಟೋಕನ್‌ಗಳಲ್ಲಿ ಕಡಿಮೆ ಅಸ್ಥಿರತೆಯ ಬಗ್ಗೆ ಹೆಚ್ಚು ವಿಷಯಗಳು.",
  "page-NEPH-tokens-defi-description": "ಇಥಿರಿಯಮ್ ಟೋಕನ್‌ಗಳಿಗೆ ಹಣಕಾಸಿನ ವ್ಯವಸ್ಥೆ.",
  "page-NEPH-tokens-nft-description": "ಇಥಿರಿಯಮ್‍ನಲ್ಲಿ ವಸ್ತುಗಳ ಮಾಲೀಕತ್ವವನ್ನು ಪ್ರತಿನಿಧಿಸುವ ಟೋಕನ್‌ಗಳು.",
  "page-NEPH-tokens-dao-description": "ಇಂಟರ್ನೆಟ್ ಸಮುದಾಯಗಳನ್ನು ಸಾಮಾನ್ಯವಾಗಿ ಟೋಕನ್ ಹೊಂದಿರುವವರು ನಿಯಂತ್ರಿಸುತ್ತಾರೆ.",
  "page-NEPH-whats-defi": "DeFi ನಲ್ಲಿ ಇನ್ನಷ್ಟು",
  "page-NEPH-whats-defi-description": "DeFi ಎಂಬುದು ಇಥಿರಿಯಮ್‍ನಲ್ಲಿ ನಿರ್ಮಿಸಲಾದ ವಿಕೇಂದ್ರೀಕೃತ ಹಣಕಾಸು ವ್ಯವಸ್ಥೆಯಾಗಿದೆ. ಈ ಅವಲೋಕನವು ನೀವು ಏನು ಮಾಡಬಹುದು ಎಂಬುದನ್ನು ವಿವರಿಸುತ್ತದೆ.",
  "page-what-is-Nephele-what-is-Nephele": "What is Nephele?"
}
